{"id":87,"code":"BMFF","shortName":"BMFF","name":"QUỸ ĐẦU TƯ TĂNG TRƯỞNG BORDIER - MB FLAGSHIP","description":"BMFF là sản phẩm quỹ mở cổ phiếu với mục tiêu đem lại tăng trưởng 15 – 20%/năm và quản trị rủi ro chặt chẽ chuyên nghiệp.","nav":16475,"managementFee":1.8,"buyMinValue":50000,"sellMin":10,"completeTransactionDuration":5,"closedOrderBookAt":"14:30","websiteURL":"https://mbcapital.com.vn/","firstIssueAt":1672678800000,"riskLevel":{"id":3,"name":"Cao"},"fundType":{"id":1,"name":"Quỹ mở"},"assetType":{"id":1,"name":"Quỹ cổ phiếu","code":"STOCK"},"owner":{"id":49227,"name":"CÔNG TY CỔ PHẦN QUẢN LÝ QUỸ ĐẦU TƯ MB","shortName":"MBCAPITAL","website":"https://mbcapital.com.vn/","avatarUrl":"https://files.fmarket.vn/pro/temp/e8e832a5-c0a2-4c56-ac1d-ab10ed1e23da.jpg"},"productNavChange":{"navToPrevious":-0.05,"navToLastYear":4.01,"navToEstablish":64.75,"navTo1Months":0.68,"navTo3Months":2.87,"navTo6Months":4.01,"navTo12Months":16.27,"navTo24Months":34.59,"navTo36Months":53.18,"navTo60Months":null,"navTo7Years":null,"navTo10Years":null,"annualizedReturn36Months":15.28,"navToBeginning":64.75,"updateAt":1782926530885},"topHoldings":[{"id":116283,"stockCode":"ACB","price":22.7,"changeFromPrevious":0.05,"changeFromPreviousPercent":0.22,"industry":"Ngân hàng","type":"STOCK","netAssetPercent":14.56,"updateAt":1781863059931,"volume":3025000,"assetValue":75322500000},{"id":116297,"stockCode":"TCB","price":34.25,"changeFromPrevious":-0.05,"changeFromPreviousPercent":-0.15,"industry":"Ngân hàng","type":"STOCK","netAssetPercent":9.09,"updateAt":1781863059931,"volume":1435000,"assetValue":46996250000},{"id":116301,"stockCode":"VIB","price":16.65,"changeFromPrevious":0.05,"changeFromPreviousPercent":0.3,"industry":"Ngân hàng","type":"STOCK","netAssetPercent":6.12,"updateAt":1781863059931,"volume":1965000,"assetValue":31636500000},{"id":116299,"stockCode":"TPB","price":16.65,"changeFromPrevious":-0.1,"changeFromPreviousPercent":-0.6,"industry":"Ngân hàng","type":"STOCK","netAssetPercent":5.29,"updateAt":1781863059931,"volume":1720000,"assetValue":27348000000},{"id":116298,"stockCode":"TCI","price":10.6,"changeFromPrevious":0.05,"changeFromPreviousPercent":0.47,"industry":"Chứng khoán","type":"STOCK","netAssetPercent":3.81,"updateAt":1781863059931,"volume":1730000,"assetValue":19722000000},{"id":116285,"stockCode":"CTG","price":34.3,"changeFromPrevious":-0.1,"changeFromPreviousPercent":-0.29,"industry":"Ngân hàng","type":"STOCK","netAssetPercent":3.73,"updateAt":1781863059931,"volume":555000,"assetValue":19314000000},{"id":116295,"stockCode":"QNS","price":48.9,"changeFromPrevious":0,"changeFromPreviousPercent":0,"industry":"Thực phẩm - Đồ uống","type":"STOCK","netAssetPercent":3.51,"updateAt":1781863059931,"volume":381600,"assetValue":18164160000},{"id":116294,"stockCode":"PVT","price":20.35,"changeFromPrevious":0.15,"changeFromPreviousPercent":0.74,"industry":"Vận tải - Kho bãi","type":"STOCK","netAssetPercent":3.33,"updateAt":1781863059931,"volume":775000,"assetValue":17205000000},{"id":116286,"stockCode":"DPR","price":39.3,"changeFromPrevious":0.35,"changeFromPreviousPercent":0.9,"industry":"Sản xuất Nhựa - Hóa chất","type":"STOCK","netAssetPercent":3.22,"updateAt":1781863059931,"volume":400000,"assetValue":16640000000},{"id":116288,"stockCode":"HPG","price":23.5,"changeFromPrevious":0.05,"changeFromPreviousPercent":0.21,"industry":"Vật liệu xây dựng","type":"STOCK","netAssetPercent":3.13,"updateAt":1781863059931,"volume":675000,"assetValue":16200000000}],"topHoldingsBond":[],"industries":[{"id":null,"industry":"Ngân hàng","assetPercent":40.97},{"id":null,"industry":"Bất động sản","assetPercent":5.25},{"id":null,"industry":"Chứng khoán","assetPercent":3.81},{"id":null,"industry":"Thực phẩm - Đồ uống","assetPercent":3.51},{"id":null,"industry":"Vận tải - Kho bãi","assetPercent":3.33},{"id":null,"industry":"Sản xuất Nhựa - Hóa chất","assetPercent":3.22},{"id":null,"industry":"Vật liệu xây dựng","assetPercent":3.13},{"id":null,"industry":"Sản xuất Thiết bị, máy móc","assetPercent":2.19},{"id":null,"industry":"Thiết bị điện","assetPercent":1.58},{"id":null,"industry":"Nông - Lâm - Ngư","assetPercent":0.97},{"id":null,"industry":"Bán lẻ","assetPercent":0.22},{"id":null,"industry":"Tiện ích","assetPercent":0.06}],"assetAllocation":[{"id":7151,"assetType":{"id":1,"code":"STOCK","name":"Cổ phiếu","colorCode":"#3FEBA2"},"assetPercent":67.25,"createAt":1781863059968,"updateAt":1781863059968},{"id":7152,"assetType":{"id":2,"code":"BOND","name":"Trái phiếu","colorCode":"#FA9F05"},"assetPercent":0.97,"createAt":1781863059968,"updateAt":1781863059968},{"id":7153,"assetType":{"id":4,"code":"OTHER","name":"Khác","colorCode":"#9B9B9B"},"assetPercent":15.47,"createAt":1781863059968,"updateAt":1781863059968},{"id":7154,"assetType":{"id":3,"code":"CASH","name":"Tiền và tương đương tiền","colorCode":"#479258"},"assetPercent":16.31,"createAt":1781863059968,"updateAt":1781863059968}],"fees":[{"type":"BUY","beginVolume":0,"endVolume":100000000,"fee":0,"feeUnitType":"MONEY","program":"Linh hoạt"},{"type":"BUY","beginVolume":100000000,"endVolume":null,"fee":0,"feeUnitType":"MONEY","program":"Linh hoạt"},{"type":"SELL","beginVolume":0,"endVolume":12,"fee":2,"feeUnitType":"MONTH","program":"Linh hoạt"},{"type":"SELL","beginVolume":12,"endVolume":24,"fee":1,"feeUnitType":"MONTH","program":"Linh hoạt"},{"type":"SELL","beginVolume":24,"endVolume":null,"fee":0,"feeUnitType":"MONTH","program":"Linh hoạt"},{"type":"TRANSFER","beginVolume":0,"endVolume":12,"fee":1.5,"feeUnitType":"MONTH","program":"Linh hoạt"},{"type":"TRANSFER","beginVolume":12,"endVolume":24,"fee":0.5,"feeUnitType":"MONTH","program":"Linh hoạt"},{"type":"TRANSFER","beginVolume":24,"endVolume":null,"fee":0,"feeUnitType":"MONTH","program":"Linh hoạt"},{"type":"TRANSFER","beginVolume":0,"endVolume":12,"fee":1.5,"feeUnitType":"MONTH","program":"Linh hoạt"},{"type":"TRANSFER","beginVolume":12,"endVolume":24,"fee":0.5,"feeUnitType":"MONTH","program":"Linh hoạt"},{"type":"TRANSFER","beginVolume":24,"endVolume":null,"fee":0,"feeUnitType":"MONTH","program":"Linh hoạt"},{"type":"TRANSFER","beginVolume":0,"endVolume":12,"fee":1.5,"feeUnitType":"MONTH","program":"Linh hoạt"},{"type":"TRANSFER","beginVolume":12,"endVolume":24,"fee":0.5,"feeUnitType":"MONTH","program":"Linh hoạt"},{"type":"TRANSFER","beginVolume":24,"endVolume":null,"fee":0,"feeUnitType":"MONTH","program":"Linh hoạt"}]}